syllabus/__init__.py
syllabus/utils.py
syllabus/core/__init__.py
syllabus/core/curriculum_base.py
syllabus/core/curriculum_sync_wrapper.py
syllabus/core/dual_curriculum_wrapper.py
syllabus/core/environment_sync_wrapper.py
syllabus/core/evaluator.py
syllabus/core/multiagent_curriculum_wrappers.py
syllabus/core/stat_recorder.py
syllabus/core/task_interface/__init__.py
syllabus/core/task_interface/reinit_task_wrapper.py
syllabus/core/task_interface/subclass_task_wrapper.py
syllabus/core/task_interface/task_env.py
syllabus/core/task_interface/task_wrapper.py
syllabus/curricula/__init__.py
syllabus/curricula/constant.py
syllabus/curricula/domain_randomization.py
syllabus/curricula/expanding_box.py
syllabus/curricula/learnability.py
syllabus/curricula/learning_progress.py
syllabus/curricula/manual.py
syllabus/curricula/omni.py
syllabus/curricula/online_learning_progress.py
syllabus/curricula/selfplay.py
syllabus/curricula/sequential.py
syllabus/curricula/simulated_annealing.py
syllabus/curricula/plr/__init__.py
syllabus/curricula/plr/central_plr_wrapper.py
syllabus/curricula/plr/direct_plr_wrapper.py
syllabus/curricula/plr/plr_wrapper.py
syllabus/curricula/plr/task_sampler.py
syllabus/examples/__init__.py
syllabus/examples/models/__init__.py
syllabus/examples/models/cartpole_model.py
syllabus/examples/models/minigrid_model copy.py
syllabus/examples/models/minigrid_model.py
syllabus/examples/models/procgen_model.py
syllabus/examples/multigrid/__init__.py
syllabus/examples/multigrid/adversarial.py
syllabus/examples/multigrid/cluttered.py
syllabus/examples/multigrid/crossing.py
syllabus/examples/multigrid/fourrooms.py
syllabus/examples/multigrid/manual_control.py
syllabus/examples/multigrid/maze.py
syllabus/examples/multigrid/mst_maze.py
syllabus/examples/multigrid/multigrid.py
syllabus/examples/multigrid/register.py
syllabus/examples/multigrid/registration.py
syllabus/examples/multigrid/window.py
syllabus/examples/task_wrappers/__init__.py
syllabus_rl-0.7.dist-info/licenses/LICENSE
syllabus_rl-0.7.dist-info/METADATA
syllabus_rl-0.7.dist-info/WHEEL
syllabus_rl-0.7.dist-info/top_level.txt
syllabus_rl-0.7.dist-info/RECORD
