Metadata-Version: 2.4
Name: Syllabus-RL
Version: 0.7
Summary: A library for training RL agent with curriculum learning
Home-page: https://github.com/RyanNavillus/Syllabus
Author: Ryan Sullivan
Author-email: Ryan Sullivan <ryanpnavillus@gmail.com>
Project-URL: Homepage, https://github.com/RyanNavillus/Syllabus
Keywords: Syllabus,AI,RL,Curriculum Learning,Unsupervised Environment Design
Classifier: Programming Language :: Python :: 3
Classifier: License :: OSI Approved :: MIT License
Classifier: Operating System :: OS Independent
Requires-Python: >=3.8
License-File: LICENSE
Requires-Dist: gymnasium>=0.28.0
Requires-Dist: numpy>=1.24.0
Requires-Dist: torch>=2.0.1
Requires-Dist: pettingzoo
Requires-Dist: joblib
Requires-Dist: ray
Provides-Extra: test
Requires-Dist: pytest>=8.1.1; extra == "test"
Requires-Dist: pytest-benchmark>=3.4.1; extra == "test"
Requires-Dist: cmake; extra == "test"
Requires-Dist: ninja; extra == "test"
Requires-Dist: gym; extra == "test"
Requires-Dist: nle>=0.9.0; extra == "test"
Requires-Dist: matplotlib>=3.7.1; extra == "test"
Requires-Dist: pygame; extra == "test"
Requires-Dist: pymunk; extra == "test"
Requires-Dist: scipy>=1.10.0; extra == "test"
Requires-Dist: tensorboard>=2.13.0; extra == "test"
Requires-Dist: shimmy; extra == "test"
Provides-Extra: docs
Requires-Dist: sphinx-tabs; extra == "docs"
Requires-Dist: sphinxcontrib-spelling; extra == "docs"
Requires-Dist: furo; extra == "docs"
Provides-Extra: all
Requires-Dist: pytest>=8.1.1; extra == "all"
Requires-Dist: pytest-benchmark>=3.4.1; extra == "all"
Requires-Dist: cmake; extra == "all"
Requires-Dist: ninja; extra == "all"
Requires-Dist: gym; extra == "all"
Requires-Dist: nle>=0.9.0; extra == "all"
Requires-Dist: matplotlib>=3.7.1; extra == "all"
Requires-Dist: pygame; extra == "all"
Requires-Dist: pymunk; extra == "all"
Requires-Dist: scipy>=1.10.0; extra == "all"
Requires-Dist: tensorboard>=2.13.0; extra == "all"
Requires-Dist: shimmy; extra == "all"
Requires-Dist: sphinx-tabs; extra == "all"
Requires-Dist: sphinxcontrib-spelling; extra == "all"
Requires-Dist: furo; extra == "all"
Dynamic: author
Dynamic: home-page
Dynamic: keywords
Dynamic: license-file
Dynamic: provides-extra
Dynamic: requires-dist
Dynamic: requires-python
